{
    "namespace-mappings" : {
        "http://www.opengis.net/citygml/2.0":                 "https://dataset-dl.liris.cnrs.fr/rdf-owl-urban-data-ontologies/Ontologies/CityGML/2.0/core#",
        "http://www.opengis.net/citygml/appearance/2.0":      "https://dataset-dl.liris.cnrs.fr/rdf-owl-urban-data-ontologies/Ontologies/CityGML/2.0/appearance#",
        "http://www.opengis.net/citygml/building/2.0":        "https://dataset-dl.liris.cnrs.fr/rdf-owl-urban-data-ontologies/Ontologies/CityGML/2.0/building#",
        "http://www.opengis.net/citygml/bridge/2.0":          "https://dataset-dl.liris.cnrs.fr/rdf-owl-urban-data-ontologies/Ontologies/CityGML/2.0/bridge#",
        "http://www.opengis.net/citygml/generics/2.0":        "https://dataset-dl.liris.cnrs.fr/rdf-owl-urban-data-ontologies/Ontologies/CityGML/2.0/generics#",
        "http://www.opengis.net/citygml/relief/2.0":          "https://dataset-dl.liris.cnrs.fr/rdf-owl-urban-data-ontologies/Ontologies/CityGML/2.0/relief#",
        "http://www.opengis.net/citygml/transportation/2.0":  "https://dataset-dl.liris.cnrs.fr/rdf-owl-urban-data-ontologies/Ontologies/CityGML/2.0/transportation#",
        "http://www.opengis.net/citygml/cityobjectgroup/2.0": "https://dataset-dl.liris.cnrs.fr/rdf-owl-urban-data-ontologies/Ontologies/CityGML/2.0/cityobjectgroup#",
        "http://www.opengis.net/citygml/landuse/2.0":         "https://dataset-dl.liris.cnrs.fr/rdf-owl-urban-data-ontologies/Ontologies/CityGML/2.0/landuse#",
        "http://www.opengis.net/citygml/tunnel/2.0":          "https://dataset-dl.liris.cnrs.fr/rdf-owl-urban-data-ontologies/Ontologies/CityGML/2.0/tunnel#",
        "http://www.opengis.net/citygml/cityfurniture/2.0":   "https://dataset-dl.liris.cnrs.fr/rdf-owl-urban-data-ontologies/Ontologies/CityGML/2.0/cityfurniture#",
        "http://www.opengis.net/citygml/vegetation/2.0":      "https://dataset-dl.liris.cnrs.fr/rdf-owl-urban-data-ontologies/Ontologies/CityGML/2.0/vegetation#",
        "http://www.opengis.net/citygml/waterbody/2.0":       "https://dataset-dl.liris.cnrs.fr/rdf-owl-urban-data-ontologies/Ontologies/CityGML/2.0/waterbody#",
        "http://www.opengis.net/gml":                         "http://www.opengis.net/ont/gml#"
    },
    "rdf-mappings" : {
        "srsName":                                      "http://www.opengis.net/ont/geosparql#coordinateDimension",
        "srsDimension":                                 "http://www.opengis.net/ont/geosparql#spatialDimension",
        "{http://www.opengis.net/gml}id":               "http://www.w3.org/2004/02/skos/core#prefLabel",
        "{http://www.opengis.net/gml}name":             "http://www.w3.org/2004/02/skos/core#altLabel",
        "{http://www.opengis.net/gml}description":      "http://www.w3.org/2004/02/skos/core#note",
        "{http://www.opengis.net/gml}boundedBy":        "http://def.isotc211.org/iso19136/2007/Feature#AbstractFeature.boundedBy",
        "{http://www.opengis.net/gml}Envelope":         "http://def.isotc211.org/iso19107/2003/CoordinateGeometry#GM_Envelope",
        "{http://www.opengis.net/gml}upperCorner":      "http://def.isotc211.org/iso19107/2003/CoordinateGeometry#GM_Envelope.upperCorner",
        "{http://www.opengis.net/gml}lowerCorner":      "http://def.isotc211.org/iso19107/2003/CoordinateGeometry#GM_Envelope.lowerCorner"
    }
}